README.md
setup.cfg
setup.py
django_model_mixins/__init__.py
django_model_mixins/apps.py
django_model_mixins/constants.py
django_model_mixins.egg-info/PKG-INFO
django_model_mixins.egg-info/SOURCES.txt
django_model_mixins.egg-info/dependency_links.txt
django_model_mixins.egg-info/requires.txt
django_model_mixins.egg-info/top_level.txt
django_model_mixins/migrations/__init__.py
django_model_mixins/mixins/__init__.py
django_model_mixins/mixins/creation_date.py
django_model_mixins/mixins/edit_date.py
django_model_mixins/mixins/random_id.py
django_model_mixins/mixins/token.py
django_model_mixins/mixins/token_generated_at.py
django_model_mixins/tests/__init__.py
django_model_mixins/tests/random_id.py
django_model_mixins/tests/token.py