Metadata-Version: 2.1
Name: django-model-mixins
Version: 0.1.2
Summary: Mixins for Django models.
Home-page: https://github.com/Myzel394/django-model-mixins
Author: Myzel394 Xyllian
Author-email: myzel394.xyllian@gmail.com
License: MIT
Download-URL: https://github.com/Myzel394/django-model-mixins/archieve/v_0.1.2.tar.gz
Keywords: django,django-utils,django-models
Platform: OS Independent
Classifier: Programming Language :: Python :: 3
Classifier: License :: OSI Approved :: MIT License
Classifier: Framework :: Django
Classifier: Intended Audience :: Developers
